notion/__init__.py
notion/adapters.py
notion/clients.py
notion/events.py
notion/exceptions.py
notion/http_status.py
notion/models.py
notion/request.py
notion/serializer.py
notion/utils.py
notion/version.py
tests/__init__.py
tests/tests_notion_client.py
pynotion_wrapper-0.2.1.dist-info/LICENSE
pynotion_wrapper-0.2.1.dist-info/METADATA
pynotion_wrapper-0.2.1.dist-info/WHEEL
pynotion_wrapper-0.2.1.dist-info/top_level.txt
pynotion_wrapper-0.2.1.dist-info/RECORD
