Metadata-Version: 2.1
Name: pynotion-wrapper
Version: 0.2.1
Summary: Python SDK for Notion API client
Home-page: https://github.com/sodrooome/notion-sdk
Author: Ryan Febriansyah
Author-email: ryanfebriansyah72@gmail.com
License: UNKNOWN
Platform: UNKNOWN
Classifier: Development Status :: 4 - Beta
Classifier: Operating System :: OS Independent
Classifier: Intended Audience :: Developers
Classifier: Natural Language :: English
Classifier: Programming Language :: Python :: 3.7
Classifier: Programming Language :: Python :: 3.8
Requires-Python: >=3.7
License-File: LICENSE
Requires-Dist: requests
